acouchbase_columnar/__init__.py
acouchbase_columnar/cluster.py
acouchbase_columnar/cluster.pyi
acouchbase_columnar/credential.py
acouchbase_columnar/database.py
acouchbase_columnar/database.pyi
acouchbase_columnar/deserializer.py
acouchbase_columnar/errors.py
acouchbase_columnar/options.py
acouchbase_columnar/query.py
acouchbase_columnar/result.py
acouchbase_columnar/scope.py
acouchbase_columnar/scope.pyi
acouchbase_columnar/protocol/__init__.py
acouchbase_columnar/protocol/cluster.py
acouchbase_columnar/protocol/cluster.pyi
acouchbase_columnar/protocol/database.py
acouchbase_columnar/protocol/database.pyi
acouchbase_columnar/protocol/query.py
acouchbase_columnar/protocol/scope.py
acouchbase_columnar/protocol/scope.pyi
acouchbase_columnar/protocol/core/__init__.py
acouchbase_columnar/protocol/core/client_adapter.py
couchbase_columnar/__init__.py
couchbase_columnar/_version.py
couchbase_columnar/cluster.py
couchbase_columnar/cluster.pyi
couchbase_columnar/credential.py
couchbase_columnar/database.py
couchbase_columnar/database.pyi
couchbase_columnar/deserializer.py
couchbase_columnar/errors.py
couchbase_columnar/options.py
couchbase_columnar/query.py
couchbase_columnar/result.py
couchbase_columnar/scope.py
couchbase_columnar/scope.pyi
couchbase_columnar/common/__init__.py
couchbase_columnar/common/credential.py
couchbase_columnar/common/deserializer.py
couchbase_columnar/common/enums.py
couchbase_columnar/common/errors.py
couchbase_columnar/common/options.py
couchbase_columnar/common/options_base.py
couchbase_columnar/common/options_base.pyi
couchbase_columnar/common/query.py
couchbase_columnar/common/result.py
couchbase_columnar/common/streaming.py
couchbase_columnar/common/core/__init__.py
couchbase_columnar/common/core/_certificates.py
couchbase_columnar/common/core/exception.py
couchbase_columnar/common/core/query.py
couchbase_columnar/common/core/result.py
couchbase_columnar/common/core/utils.py
couchbase_columnar/common/core/nonprod_certificates/__init__.py
couchbase_columnar-1.0.1.dist-info/licenses/LICENSE
couchbase_columnar-1.0.1.dist-info/METADATA
couchbase_columnar-1.0.1.dist-info/WHEEL
couchbase_columnar-1.0.1.dist-info/top_level.txt
couchbase_columnar-1.0.1.dist-info/RECORD
