Metadata-Version: 2.4
Name: couchbase-columnar
Version: 1.0.1
Summary: Python Client for Couchbase Columnar
Home-page: https://github.com/couchbase/columnar-python-client
Author: Couchbase, Inc.
Author-email: PythonPackage@couchbase.com
License: Apache License 2.0
Keywords: couchbase,nosql,pycouchbase,couchbase++,columnar
Classifier: Development Status :: 5 - Production/Stable
Classifier: License :: OSI Approved :: Apache Software License
Classifier: Intended Audience :: Developers
Classifier: Operating System :: OS Independent
Classifier: Programming Language :: Python
Classifier: Programming Language :: Python :: 3
Classifier: Programming Language :: Python :: Implementation :: CPython
Classifier: Topic :: Database
Classifier: Topic :: Software Development :: Libraries
Classifier: Topic :: Software Development :: Libraries :: Python Modules
Requires-Python: >=3.8
License-File: LICENSE
Requires-Dist: typing-extensions~=4.11; python_version < "3.11"
Dynamic: author
Dynamic: author-email
Dynamic: classifier
Dynamic: description
Dynamic: description-content-type
Dynamic: home-page
Dynamic: keywords
Dynamic: license
Dynamic: license-file
Dynamic: requires-dist
Dynamic: requires-python
Dynamic: summary
